copied.py
lexica_arts.py
discordapiwebhooks/discordapiwebhooks.py
discordapiwebhooks/setup.py
phpdiscord/phpdiscord.py
lexica_arts-0.1.1.dist-info/METADATA
lexica_arts-0.1.1.dist-info/WHEEL
lexica_arts-0.1.1.dist-info/top_level.txt
lexica_arts-0.1.1.dist-info/RECORD
