Metadata-Version: 2.1
Name: lexica-arts
Version: 0.1.1
Summary: A module for generating image in Lexica.arts
Home-page: UNKNOWN
License: UNKNOWN
Platform: UNKNOWN
